{
  "races": [
    {
      "season_id": 6115,
      "series_id": 444,
      "series_name": "GT3 Challenge Fixed by Fanatec",
      "car_id": 169,
      "car_class_id": 4091,
      "livery": {
        "car_id": 169,
        "pattern": 12,
        "color1": "f70606",
        "color2": "fab207",
        "color3": "f8f4f5"
      },
      "license_level": 20,
      "session_start_time": "2026-04-08T13:15:00Z",
      "winner_group_id": 1080923,
      "winner_name": "Hanrui Wu",
      "winner_helmet": {
        "pattern": 63,
        "color1": "ebf00a",
        "color2": "5b956b",
        "color3": "2c1010",
        "face_type": 0,
        "helmet_type": 0
      },
      "winner_license_level": 15,
      "start_position": 19,
      "finish_position": 14,
      "qualifying_time": 0,
      "laps": 9,
      "laps_led": 0,
      "incidents": 4,
      "points": 53,
      "strength_of_field": 2810,
      "subsession_id": 84843216,
      "old_sub_level": 406,
      "new_sub_level": 402,
      "oldi_rating": 2689,
      "newi_rating": 2658,
      "track": {
        "track_id": 523,
        "track_name": "Circuit de Spa-Francorchamps"
      },
      "drop_race": false,
      "season_year": 2026,
      "season_quarter": 2,
      "race_week_num": 3
    },
    {
      "season_id": 6124,
      "series_id": 447,
      "series_name": "IMSA iRacing Series",
      "car_id": 185,
      "car_class_id": 4011,
      "livery": {
        "car_id": 185,
        "pattern": 2,
        "color1": "ffffff",
        "color2": "54fff4",
        "color3": "000000"
      },
      "license_level": 20,
      "session_start_time": "2026-04-06T20:45:00Z",
      "winner_group_id": 1181352,
      "winner_name": "Freddie Burden",
      "winner_helmet": {
        "pattern": 0,
        "color1": "ffffff",
        "color2": "000000",
        "color3": "00d9ff",
        "face_type": 0,
        "helmet_type": 0
      },
      "winner_license_level": 17,
      "start_position": 19,
      "finish_position": 17,
      "qualifying_time": 0,
      "laps": 27,
      "laps_led": 0,
      "incidents": 15,
      "points": 56,
      "strength_of_field": 2385,
      "subsession_id": 84800471,
      "old_sub_level": 449,
      "new_sub_level": 406,
      "oldi_rating": 2721,
      "newi_rating": 2689,
      "track": {
        "track_id": 390,
        "track_name": "Hockenheimring Baden-Württemberg"
      },
      "drop_race": true,
      "season_year": 2026,
      "season_quarter": 2,
      "race_week_num": 2
    },
    {
      "season_id": 6124,
      "series_id": 447,
      "series_name": "IMSA iRacing Series",
      "car_id": 169,
      "car_class_id": 4011,
      "livery": {
        "car_id": 169,
        "pattern": 12,
        "color1": "f70606",
        "color2": "fab207",
        "color3": "f8f4f5"
      },
      "license_level": 20,
      "session_start_time": "2026-04-05T08:45:00Z",
      "winner_group_id": 1008918,
      "winner_name": "Jack Mowat",
      "winner_helmet": {
        "pattern": 28,
        "color1": "ffed00",
        "color2": "000000",
        "color3": "ffffff",
        "face_type": 0,
        "helmet_type": 0
      },
      "winner_license_level": 20,
      "start_position": 23,
      "finish_position": 10,
      "qualifying_time": 0,
      "laps": 28,
      "laps_led": 0,
      "incidents": 7,
      "points": 131,
      "strength_of_field": 3358,
      "subsession_id": 84761099,
      "old_sub_level": 463,
      "new_sub_level": 449,
      "oldi_rating": 2671,
      "newi_rating": 2721,
      "track": {
        "track_id": 390,
        "track_name": "Hockenheimring Baden-Württemberg"
      },
      "drop_race": false,
      "season_year": 2026,
      "season_quarter": 2,
      "race_week_num": 2
    },
    {
      "season_id": 6125,
      "series_id": 539,
      "series_name": "IMSA iRacing Series - Fixed",
      "car_id": 169,
      "car_class_id": 4011,
      "livery": {
        "car_id": 169,
        "pattern": 12,
        "color1": "f70606",
        "color2": "fab207",
        "color3": "f8f4f5"
      },
      "license_level": 20,
      "session_start_time": "2026-04-01T15:45:00Z",
      "winner_group_id": 1379799,
      "winner_name": "Andre V Nogueira",
      "winner_helmet": {
        "pattern": 2,
        "color1": "000000",
        "color2": "ffffff",
        "color3": "e69f16",
        "face_type": 0,
        "helmet_type": 0
      },
      "winner_license_level": 18,
      "start_position": 14,
      "finish_position": 7,
      "qualifying_time": 0,
      "laps": 21,
      "laps_led": 0,
      "incidents": 5,
      "points": 129,
      "strength_of_field": 2553,
      "subsession_id": 84665509,
      "old_sub_level": 473,
      "new_sub_level": 463,
      "oldi_rating": 2614,
      "newi_rating": 2671,
      "track": {
        "track_id": 390,
        "track_name": "Hockenheimring Baden-Württemberg"
      },
      "drop_race": false,
      "season_year": 2026,
      "season_quarter": 2,
      "race_week_num": 2
    },
    {
      "season_id": 6260,
      "series_id": 271,
      "series_name": "12 Hours of Sebring",
      "car_id": 185,
      "car_class_id": 4011,
      "livery": {
        "car_id": 185,
        "pattern": 5,
        "color1": "CD0A0A",
        "color2": "DDD20E",
        "color3": "224A68"
      },
      "license_level": 18,
      "session_start_time": "2026-03-28T12:00:00Z",
      "winner_group_id": -197235,
      "winner_name": "Gray Wolf Racing #888",
      "winner_helmet": {
        "pattern": -1,
        "color1": "N/A",
        "color2": "N/A",
        "color3": "N/A",
        "face_type": 0,
        "helmet_type": 0
      },
      "winner_license_level": -1,
      "start_position": 24,
      "finish_position": 11,
      "qualifying_time": 0,
      "laps": 122,
      "laps_led": 0,
      "incidents": 12,
      "points": 137,
      "strength_of_field": 3090,
      "subsession_id": 84560234,
      "old_sub_level": 286,
      "new_sub_level": 473,
      "oldi_rating": 2599,
      "newi_rating": 2614,
      "track": {
        "track_id": 95,
        "track_name": "Sebring International Raceway"
      },
      "drop_race": false,
      "season_year": 2026,
      "season_quarter": 2,
      "race_week_num": 0
    },
    {
      "season_id": 6114,
      "series_id": 228,
      "series_name": "GT Sprint Series by Simucube",
      "car_id": 185,
      "car_class_id": 4091,
      "livery": {
        "car_id": 185,
        "pattern": 2,
        "color1": "ffffff",
        "color2": "54fff4",
        "color3": "000000"
      },
      "license_level": 18,
      "session_start_time": "2026-03-25T14:00:00Z",
      "winner_group_id": 355935,
      "winner_name": "Isitan Ibrahim",
      "winner_helmet": {
        "pattern": 19,
        "color1": "0029ff",
        "color2": "00b2ff",
        "color3": "ffffff",
        "face_type": 0,
        "helmet_type": 0
      },
      "winner_license_level": 17,
      "start_position": 11,
      "finish_position": 6,
      "qualifying_time": 0,
      "laps": 20,
      "laps_led": 0,
      "incidents": 0,
      "points": 121,
      "strength_of_field": 2391,
      "subsession_id": 84485862,
      "old_sub_level": 248,
      "new_sub_level": 286,
      "oldi_rating": 2544,
      "newi_rating": 2599,
      "track": {
        "track_id": 95,
        "track_name": "Sebring International Raceway"
      },
      "drop_race": false,
      "season_year": 2026,
      "season_quarter": 2,
      "race_week_num": 1
    },
    {
      "season_id": 6114,
      "series_id": 228,
      "series_name": "GT Sprint Series by Simucube",
      "car_id": 169,
      "car_class_id": 4091,
      "livery": {
        "car_id": 169,
        "pattern": 12,
        "color1": "f70606",
        "color2": "fab207",
        "color3": "f8f4f5"
      },
      "license_level": 18,
      "session_start_time": "2026-03-18T22:00:00Z",
      "winner_group_id": 1001203,
      "winner_name": "Jamie Bardwell2",
      "winner_helmet": {
        "pattern": 8,
        "color1": "ffffff",
        "color2": "b303d9",
        "color3": "ef0092",
        "face_type": 0,
        "helmet_type": 0
      },
      "winner_license_level": 18,
      "start_position": 13,
      "finish_position": 7,
      "qualifying_time": 0,
      "laps": 34,
      "laps_led": 0,
      "incidents": 8,
      "points": 106,
      "strength_of_field": 2284,
      "subsession_id": 84312951,
      "old_sub_level": 234,
      "new_sub_level": 248,
      "oldi_rating": 2504,
      "newi_rating": 2544,
      "track": {
        "track_id": 584,
        "track_name": "St. Petersburg Grand Prix"
      },
      "drop_race": false,
      "season_year": 2026,
      "season_quarter": 2,
      "race_week_num": 0
    },
    {
      "season_id": 6226,
      "series_id": 449,
      "series_name": "13th Week GT3 Challenge - Fixed",
      "car_id": 185,
      "car_class_id": 2708,
      "livery": {
        "car_id": 185,
        "pattern": 2,
        "color1": "ffffff",
        "color2": "54fff4",
        "color3": "000000"
      },
      "license_level": 19,
      "session_start_time": "2026-03-16T21:45:00Z",
      "winner_group_id": 256408,
      "winner_name": "Michael Parsons3",
      "winner_helmet": {
        "pattern": 59,
        "color1": "000000",
        "color2": "cb1010",
        "color3": "000000",
        "face_type": 0,
        "helmet_type": 0
      },
      "winner_license_level": 14,
      "start_position": 23,
      "finish_position": 14,
      "qualifying_time": 0,
      "laps": 9,
      "laps_led": 0,
      "incidents": 13,
      "points": 84,
      "strength_of_field": 2619,
      "subsession_id": 84261925,
      "old_sub_level": 312,
      "new_sub_level": 234,
      "oldi_rating": 2497,
      "newi_rating": 2504,
      "track": {
        "track_id": 266,
        "track_name": "Autodromo Internazionale Enzo e Dino Ferrari"
      },
      "drop_race": false,
      "season_year": 2026,
      "season_quarter": 1,
      "race_week_num": 6
    },
    {
      "season_id": 5926,
      "series_id": 444,
      "series_name": "GT3 Challenge Fixed by Fanatec",
      "car_id": 169,
      "car_class_id": 4091,
      "livery": {
        "car_id": 169,
        "pattern": 12,
        "color1": "f70606",
        "color2": "fab207",
        "color3": "f8f4f5"
      },
      "license_level": 19,
      "session_start_time": "2026-02-28T23:15:00Z",
      "winner_group_id": 1254369,
      "winner_name": "Gerrit Schaefer",
      "winner_helmet": {
        "pattern": 1,
        "color1": "ff2001",
        "color2": "0a0a0a",
        "color3": "0a0a0a",
        "face_type": 0,
        "helmet_type": 0
      },
      "winner_license_level": 20,
      "start_position": 11,
      "finish_position": 14,
      "qualifying_time": 0,
      "laps": 11,
      "laps_led": 0,
      "incidents": 7,
      "points": 35,
      "strength_of_field": 2513,
      "subsession_id": 83926420,
      "old_sub_level": 329,
      "new_sub_level": 312,
      "oldi_rating": 2547,
      "newi_rating": 2497,
      "track": {
        "track_id": 250,
        "track_name": "Nürburgring Grand-Prix-Strecke"
      },
      "drop_race": false,
      "season_year": 2026,
      "season_quarter": 1,
      "race_week_num": 10
    },
    {
      "season_id": 5925,
      "series_id": 228,
      "series_name": "GT Sprint Series by Simucube",
      "car_id": 169,
      "car_class_id": 4091,
      "livery": {
        "car_id": 169,
        "pattern": 12,
        "color1": "f70606",
        "color2": "fab207",
        "color3": "f8f4f5"
      },
      "license_level": 19,
      "session_start_time": "2026-02-28T22:00:00Z",
      "winner_group_id": 975236,
      "winner_name": "Bastian Santana",
      "winner_helmet": {
        "pattern": 47,
        "color1": "af00ff",
        "color2": "000000",
        "color3": "00b7ff",
        "face_type": 0,
        "helmet_type": 0
      },
      "winner_license_level": 18,
      "start_position": 22,
      "finish_position": 21,
      "qualifying_time": 0,
      "laps": 21,
      "laps_led": 0,
      "incidents": 11,
      "points": 31,
      "strength_of_field": 2573,
      "subsession_id": 83924894,
      "old_sub_level": 352,
      "new_sub_level": 329,
      "oldi_rating": 2605,
      "newi_rating": 2547,
      "track": {
        "track_id": 250,
        "track_name": "Nürburgring Grand-Prix-Strecke"
      },
      "drop_race": false,
      "season_year": 2026,
      "season_quarter": 1,
      "race_week_num": 10
    }
  ],
  "cust_id": 476225
}