{
  "races": [
    {
      "season_id": 6305,
      "series_id": 596,
      "series_name": "iRacing GT3 Regional Tour - Europe",
      "car_id": 169,
      "car_class_id": 2708,
      "livery": {
        "car_id": 169,
        "pattern": 7,
        "color1": "2e358f",
        "color2": "ec232d",
        "color3": "0a0a0a"
      },
      "license_level": 14,
      "session_start_time": "2026-06-24T20:45:00Z",
      "winner_group_id": 1190523,
      "winner_name": "Giovanni Quaggia",
      "winner_helmet": {
        "pattern": 65,
        "color1": "2d2727",
        "color2": "1c1b1f",
        "color3": "241e1e",
        "face_type": 0,
        "helmet_type": 0
      },
      "winner_license_level": 15,
      "start_position": 13,
      "finish_position": 10,
      "qualifying_time": 0,
      "laps": 13,
      "laps_led": 0,
      "incidents": 16,
      "points": 58,
      "strength_of_field": 2211,
      "subsession_id": 86700098,
      "old_sub_level": 206,
      "new_sub_level": 150,
      "oldi_rating": 1970,
      "newi_rating": 1968,
      "track": {
        "track_id": 180,
        "track_name": "Oulton Park Circuit"
      },
      "drop_race": false,
      "season_year": 2026,
      "season_quarter": 3,
      "race_week_num": 1
    },
    {
      "season_id": 6266,
      "series_id": 571,
      "series_name": "BMW M2 Cup",
      "car_id": 216,
      "car_class_id": 4108,
      "livery": {
        "car_id": 216,
        "pattern": 3,
        "color1": "2e358f",
        "color2": "ec232d",
        "color3": "0a0a0a"
      },
      "license_level": 14,
      "session_start_time": "2026-06-18T20:45:00Z",
      "winner_group_id": 1509819,
      "winner_name": "Karol Pasiewicz2",
      "winner_helmet": {
        "pattern": 1,
        "color1": "2e358f",
        "color2": "ec232d",
        "color3": "0a0a0a",
        "face_type": 0,
        "helmet_type": 0
      },
      "winner_license_level": 6,
      "start_position": 3,
      "finish_position": 6,
      "qualifying_time": 0,
      "laps": 7,
      "laps_led": 0,
      "incidents": 11,
      "points": 61,
      "strength_of_field": 1925,
      "subsession_id": 86547578,
      "old_sub_level": 228,
      "new_sub_level": 206,
      "oldi_rating": 1964,
      "newi_rating": 1970,
      "track": {
        "track_id": 166,
        "track_name": "Okayama International Circuit"
      },
      "drop_race": true,
      "season_year": 2026,
      "season_quarter": 3,
      "race_week_num": 0
    },
    {
      "season_id": 6266,
      "series_id": 571,
      "series_name": "BMW M2 Cup",
      "car_id": 216,
      "car_class_id": 4108,
      "livery": {
        "car_id": 216,
        "pattern": 3,
        "color1": "2e358f",
        "color2": "ec232d",
        "color3": "0a0a0a"
      },
      "license_level": 14,
      "session_start_time": "2026-06-18T20:15:00Z",
      "winner_group_id": 1052337,
      "winner_name": "Calvin Campbell",
      "winner_helmet": {
        "pattern": 57,
        "color1": "00fff0",
        "color2": "ffffff",
        "color3": "000000",
        "face_type": 0,
        "helmet_type": 0
      },
      "winner_license_level": 14,
      "start_position": 8,
      "finish_position": 6,
      "qualifying_time": 0,
      "laps": 7,
      "laps_led": 0,
      "incidents": 5,
      "points": 64,
      "strength_of_field": 2023,
      "subsession_id": 86547054,
      "old_sub_level": 233,
      "new_sub_level": 228,
      "oldi_rating": 1953,
      "newi_rating": 1964,
      "track": {
        "track_id": 166,
        "track_name": "Okayama International Circuit"
      },
      "drop_race": false,
      "season_year": 2026,
      "season_quarter": 3,
      "race_week_num": 0
    },
    {
      "season_id": 6110,
      "series_id": 299,
      "series_name": "iRacing Porsche Cup by CONSPIT",
      "car_id": 208,
      "car_class_id": 4093,
      "livery": {
        "car_id": 208,
        "pattern": 2,
        "color1": "2E358F",
        "color2": "EC232D",
        "color3": "0A0A0A"
      },
      "license_level": 14,
      "session_start_time": "2026-06-05T21:45:00Z",
      "winner_group_id": 835811,
      "winner_name": "Greg Hovesen",
      "winner_helmet": {
        "pattern": 28,
        "color1": "000000",
        "color2": "00ffff",
        "color3": "ff00fc",
        "face_type": 0,
        "helmet_type": 0
      },
      "winner_license_level": 19,
      "start_position": 16,
      "finish_position": 16,
      "qualifying_time": 0,
      "laps": 19,
      "laps_led": 0,
      "incidents": 14,
      "points": 49,
      "strength_of_field": 2315,
      "subsession_id": 86292633,
      "old_sub_level": 250,
      "new_sub_level": 233,
      "oldi_rating": 1968,
      "newi_rating": 1953,
      "track": {
        "track_id": 584,
        "track_name": "St. Petersburg Grand Prix"
      },
      "drop_race": false,
      "season_year": 2026,
      "season_quarter": 2,
      "race_week_num": 11
    },
    {
      "season_id": 6111,
      "series_id": 476,
      "series_name": "iRacing Porsche Cup - Fixed by CONSPIT",
      "car_id": 208,
      "car_class_id": 4093,
      "livery": {
        "car_id": 208,
        "pattern": 2,
        "color1": "2E358F",
        "color2": "EC232D",
        "color3": "0A0A0A"
      },
      "license_level": 14,
      "session_start_time": "2026-06-05T20:45:00Z",
      "winner_group_id": 1439110,
      "winner_name": "Kohr Kevin",
      "winner_helmet": {
        "pattern": 1,
        "color1": "ec232d",
        "color2": "ffffff",
        "color3": "2e358f",
        "face_type": 0,
        "helmet_type": 0
      },
      "winner_license_level": 10,
      "start_position": 9,
      "finish_position": 9,
      "qualifying_time": 0,
      "laps": 21,
      "laps_led": 0,
      "incidents": 8,
      "points": 69,
      "strength_of_field": 1812,
      "subsession_id": 86291471,
      "old_sub_level": 244,
      "new_sub_level": 250,
      "oldi_rating": 1951,
      "newi_rating": 1968,
      "track": {
        "track_id": 584,
        "track_name": "St. Petersburg Grand Prix"
      },
      "drop_race": false,
      "season_year": 2026,
      "season_quarter": 2,
      "race_week_num": 11
    },
    {
      "season_id": 6117,
      "series_id": 595,
      "series_name": "iRacing GT3 Regional Tour - Americas",
      "car_id": 169,
      "car_class_id": 4091,
      "livery": {
        "car_id": 169,
        "pattern": 7,
        "color1": "2e358f",
        "color2": "ec232d",
        "color3": "0a0a0a"
      },
      "license_level": 14,
      "session_start_time": "2026-05-29T20:45:00Z",
      "winner_group_id": 1420460,
      "winner_name": "Julian Hakendahl",
      "winner_helmet": {
        "pattern": 12,
        "color1": "fffc00",
        "color2": "00f0ff",
        "color3": "5cf5ff",
        "face_type": 0,
        "helmet_type": 0
      },
      "winner_license_level": 14,
      "start_position": 10,
      "finish_position": 9,
      "qualifying_time": 0,
      "laps": 17,
      "laps_led": 0,
      "incidents": 7,
      "points": 35,
      "strength_of_field": 1526,
      "subsession_id": 86113203,
      "old_sub_level": 241,
      "new_sub_level": 244,
      "oldi_rating": 1990,
      "newi_rating": 1951,
      "track": {
        "track_id": 584,
        "track_name": "St. Petersburg Grand Prix"
      },
      "drop_race": false,
      "season_year": 2026,
      "season_quarter": 2,
      "race_week_num": 10
    },
    {
      "season_id": 6118,
      "series_id": 596,
      "series_name": "iRacing GT3 Regional Tour - Europe",
      "car_id": 169,
      "car_class_id": 4091,
      "livery": {
        "car_id": 169,
        "pattern": 7,
        "color1": "2e358f",
        "color2": "ec232d",
        "color3": "0a0a0a"
      },
      "license_level": 14,
      "session_start_time": "2026-05-04T20:45:00Z",
      "winner_group_id": 1378838,
      "winner_name": "Francesco Puleo",
      "winner_helmet": {
        "pattern": 1,
        "color1": "2e358f",
        "color2": "ec232d",
        "color3": "0a0a0a",
        "face_type": 0,
        "helmet_type": 0
      },
      "winner_license_level": 14,
      "start_position": 5,
      "finish_position": 1,
      "qualifying_time": 0,
      "laps": 12,
      "laps_led": 12,
      "incidents": 2,
      "points": 118,
      "strength_of_field": 1919,
      "subsession_id": 85499053,
      "old_sub_level": 222,
      "new_sub_level": 241,
      "oldi_rating": 1895,
      "newi_rating": 1990,
      "track": {
        "track_id": 266,
        "track_name": "Autodromo Internazionale Enzo e Dino Ferrari"
      },
      "drop_race": false,
      "season_year": 2026,
      "season_quarter": 2,
      "race_week_num": 6
    },
    {
      "season_id": 6118,
      "series_id": 596,
      "series_name": "iRacing GT3 Regional Tour - Europe",
      "car_id": 169,
      "car_class_id": 4091,
      "livery": {
        "car_id": 169,
        "pattern": 7,
        "color1": "2e358f",
        "color2": "ec232d",
        "color3": "0a0a0a"
      },
      "license_level": 14,
      "session_start_time": "2026-05-03T20:45:00Z",
      "winner_group_id": 1112215,
      "winner_name": "Arturo Martin",
      "winner_helmet": {
        "pattern": 27,
        "color1": "000000",
        "color2": "ffffff",
        "color3": "ff4600",
        "face_type": 0,
        "helmet_type": 0
      },
      "winner_license_level": 17,
      "start_position": 9,
      "finish_position": 12,
      "qualifying_time": 0,
      "laps": 12,
      "laps_led": 0,
      "incidents": 7,
      "points": 42,
      "strength_of_field": 1991,
      "subsession_id": 85475001,
      "old_sub_level": 219,
      "new_sub_level": 222,
      "oldi_rating": 1919,
      "newi_rating": 1895,
      "track": {
        "track_id": 266,
        "track_name": "Autodromo Internazionale Enzo e Dino Ferrari"
      },
      "drop_race": true,
      "season_year": 2026,
      "season_quarter": 2,
      "race_week_num": 6
    },
    {
      "season_id": 6118,
      "series_id": 596,
      "series_name": "iRacing GT3 Regional Tour - Europe",
      "car_id": 169,
      "car_class_id": 4091,
      "livery": {
        "car_id": 169,
        "pattern": 7,
        "color1": "2e358f",
        "color2": "ec232d",
        "color3": "0a0a0a"
      },
      "license_level": 14,
      "session_start_time": "2026-05-03T16:45:00Z",
      "winner_group_id": 1224787,
      "winner_name": "Justin Grzella",
      "winner_helmet": {
        "pattern": 1,
        "color1": "ff0000",
        "color2": "ff0000",
        "color3": "0a0a0a",
        "face_type": 0,
        "helmet_type": 0
      },
      "winner_license_level": 14,
      "start_position": 6,
      "finish_position": 4,
      "qualifying_time": 0,
      "laps": 12,
      "laps_led": 0,
      "incidents": 3,
      "points": 101,
      "strength_of_field": 2013,
      "subsession_id": 85470321,
      "old_sub_level": 203,
      "new_sub_level": 219,
      "oldi_rating": 1853,
      "newi_rating": 1919,
      "track": {
        "track_id": 266,
        "track_name": "Autodromo Internazionale Enzo e Dino Ferrari"
      },
      "drop_race": false,
      "season_year": 2026,
      "season_quarter": 2,
      "race_week_num": 6
    },
    {
      "season_id": 6118,
      "series_id": 596,
      "series_name": "iRacing GT3 Regional Tour - Europe",
      "car_id": 169,
      "car_class_id": 4091,
      "livery": {
        "car_id": 169,
        "pattern": 7,
        "color1": "2e358f",
        "color2": "ec232d",
        "color3": "0a0a0a"
      },
      "license_level": 14,
      "session_start_time": "2026-05-03T15:45:00Z",
      "winner_group_id": 1291646,
      "winner_name": "Max Lorente2",
      "winner_helmet": {
        "pattern": 1,
        "color1": "231f20",
        "color2": "e41e26",
        "color3": "ffffff",
        "face_type": 0,
        "helmet_type": 0
      },
      "winner_license_level": 14,
      "start_position": 9,
      "finish_position": 15,
      "qualifying_time": 0,
      "laps": 10,
      "laps_led": 0,
      "incidents": 10,
      "points": 20,
      "strength_of_field": 1862,
      "subsession_id": 85469179,
      "old_sub_level": 209,
      "new_sub_level": 203,
      "oldi_rating": 1916,
      "newi_rating": 1853,
      "track": {
        "track_id": 266,
        "track_name": "Autodromo Internazionale Enzo e Dino Ferrari"
      },
      "drop_race": true,
      "season_year": 2026,
      "season_quarter": 2,
      "race_week_num": 6
    }
  ],
  "cust_id": 1378838
}